Workbook

Sheet Raw_Data
A1: Metric | B1: FY 2024 ($M) | C1: FY 2025 ($M)
A2: Revenue | B2: 1116.2 | C2: 2725.9
A3: Production Costs (O&M + Handling) | B3: 412.4 | C3: 752.6
A4: Royalties | B4: 146 | C4: 475.3
A5: DD&A (Depreciation) | B5: 193.8 | C5: 549.2
A6: Regulatory Fees | B6: 11.6 | C6: 44.2 | E6: NGL Revenue | F6: =C2-(C17*C19)-Sensitivity_Model!B17 -> 79.346
A7: G&A Expenses | B7: 145.7 | C7: 249.5
A8: Impairment + Fair Value Loss | B8: 17.9 | C8: 37.3
A9: Other Income | B9: 37.1 | C9: 57.5
A10: Net Finance Costs | B10: 59.8 | C10: 177.4
A11: Other Financial Income | B11: 100.4 | C11: 0
A12: Income Tax Expense | B12: 126.2 | C12: 338.8
A13: Net Income | B13: 140.5 | C13: 159.1
A15: Production Metric | B15: FY 2024 ($M) | C15: FY 2025 ($M)
A16: Total Production (boepd) | B16: 52947 | C16: 131506
A17: Oil Volumes Lifted (Mbbls) | B17: 11.1 | C17: 31.6
A18: Gas Volumes (Bscf) | B18: 93.6 | C18: 144.2
A19: Average Realised Oil Price ($/bbl) | B19: 80.04 | C19: 70.29
A20: Average Realised Gas Price ($/Mscf) | B20: 2.87 | C20: 2.95
A21: Unit Production Cost ($/boe) | B21: 16.5 | C21: 15.7
A23: Ratio | B23: FY 2024 ($M) | C23: FY 2025 ($M)
A24: Gross Profit | B24: =B2-(B3+B4+B5+B6) -> 352.4 | C24: =C2-(C3+C4+C5+C6) -> 904.6
A25: Gross Margin % | B25: =B24/B2 -> 0.31571403 | C25: =C24/C2 -> 0.3318537
A26: EBITDA | B26: =B13+B12+B10+B5 -> 520.3 | C26: =C13+C12+C10+C5 -> 1224.5
A27: EBITDA Margin % | B27: =B26/B2 -> 0.4661351 | C27: =C26/C2 -> 0.44920944
A28: Net Income Margin % | B28: =B13/B2 -> 0.1258735 | C28: =C13/C2 -> 0.058366044
A29: Effective Tax Rate % | B29: =B12/(B13+B12) -> 0.47319085 | C29: =C12/(C13+C12) -> 0.68045792
A30: Revenue per boe ($) | B30: =(B2*1000000)/(B16*365) -> 57.757421 | C30: =(C2*1000000)/(C16*365) -> 56.78995
A31: Cost of Sales per boe ($) | B31: =((B3+B4+B5+B6)*1000000)/(B16*365) -> 39.522593 | C31: =((C3+C4+C5+C6)*1000000)/(C16*365) -> 37.943995

Sheet Cost_Breakdown
A1: Item | B1: FY 2024 $M | C1: FY 2025 $M | D1: Change $M | F1: Item | G1: Change $M
A2: Revenue | B2: =Raw_Data!B2 -> 1116.2 | C2: =Raw_Data!C2 -> 2725.9 | D2: =C2-B2 -> 1609.7 | F2: Revenue Increase | G2: =D2 -> 1609.7
A3: Production Costs | B3: =Raw_Data!B3 -> 412.4 | C3: =Raw_Data!C3 -> 752.6 | D3: =C3-B3 -> 340.2 | F3: Production increase | G3: =D3 -> 340.2
A4: Royalties | B4: =Raw_Data!B4 -> 146 | C4: =Raw_Data!C4 -> 475.3 | D4: =C4-B4 -> 329.3 | F4: Royalties | G4: =D4 -> 329.3
A5: DD & A | B5: =Raw_Data!B5 -> 193.8 | C5: =Raw_Data!C5 -> 549.2 | D5: =C5-B5 -> 355.4 | F5: DD & A | G5: =D5 -> 355.4
A6: Regulatory Fees | B6: =Raw_Data!B6 -> 11.6 | C6: =Raw_Data!C6 -> 44.2 | D6: =C6-B6 -> 32.6 | F6: Regulatory Fees | G6: =D6 -> 32.6
A7: Gross Profit | B7: =Raw_Data!B24 -> 352.4 | C7: =Raw_Data!C24 -> 904.6 | D7: =C7-B7 -> 552.2 | F7: G&A Expenses | G7: =D8 -> 103.8
A8: G & A Expenses | B8: =Raw_Data!B7 -> 145.7 | C8: =Raw_Data!C7 -> 249.5 | D8: =C8-B8 -> 103.8 | F8: Impairment + Fair Value | G8: =D9 -> 19.4
A9: Impairment + Fair Value | B9: =Raw_Data!B8 -> 17.9 | C9: =Raw_Data!C8 -> 37.3 | D9: =C9-B9 -> 19.4 | F9: Other Income | G9: =D10 -> 20.4
A10: Other Income | B10: =Raw_Data!B9 -> 37.1 | C10: =Raw_Data!C9 -> 57.5 | D10: =C10-B10 -> 20.4 | F10: Net Finance Costs | G10: =D12 -> 117.6
A11: Operating Profit | B11: =Raw_Data!B2-Raw_Data!B3-Raw_Data!B4-Raw_Data!B5-Raw_Data!B6-Raw_Data!B7-Raw_Data!B8+Raw_Data!B9+Raw_Data!B11 -> 326.3 | C11: =Raw_Data!C2-Raw_Data!C3-Raw_Data!C4-Raw_Data!C5-Raw_Data!C6-Raw_Data!C7-Raw_Data!C8+Raw_Data!C9 -> 675.3 | D11: =C11-B11 -> 349 | F11: Income Tax | G11: =D14 -> 212.6
A12: Net Finance Costs | B12: =Raw_Data!B10 -> 59.8 | C12: =Raw_Data!C10 -> 177.4 | D12: =C12-B12 -> 117.6 | F12: Net Income Change | G12: =D15 -> 18.6
A13: Profit Before Tax | B13: =B11-B12 -> 266.5 | C13: =C11-C12 -> 497.9 | D13: =C13-B13 -> 231.4
A14: Income Tax | B14: =Raw_Data!B12 -> 126.2 | C14: =Raw_Data!C12 -> 338.8 | D14: =C14-B14 -> 212.6
A15: Net Income | B15: =Raw_Data!B13 -> 140.5 | C15: =Raw_Data!C13 -> 159.1 | D15: =C15-B15 -> 18.6
A16: Other Financial Income | B16: =Raw_Data!B11 -> 100.4 | C16: =Raw_Data!C11 -> 0 | D16: =C16-B16 -> -100.4
A21: Operational Margin % | B21: =B11/B2 -> 0.29233112 | C21: =C11/C2 -> 0.24773469

Sheet Sensitivity_Model
A1: Input | B1: Value
A2: FY 2025 Oil Volumes Lifted (Mbbls) | B2: =Raw_Data!C17 -> 31.6
A3: FY 2025 Gas Revenue ($M) | B3: =Raw_Data!C18*Raw_Data!C20 -> 425.39
A4: Royalty Rate (% of Revenue) | B4: =Raw_Data!C4/Raw_Data!C2 -> 0.17436443
A5: Fixed Production Costs ($M) | B5: =Raw_Data!C3 -> 752.6
A6: Fixed DD&A ($M) | B6: =Raw_Data!C5 -> 549.2
A7: Fixed Regualatory Fees ($M) | B7: =Raw_Data!C6 -> 44.2
A8: Fixed G & A ($M) | B8: =Raw_Data!C7 -> 249.5
A9: Fixed Other Income ($M) | B9: =Raw_Data!C9 -> 57.5
A10: Fixed Net Finance Costs ($M) | B10: =Raw_Data!C10 -> 177.4
A11: Effective Tax Rate (%) | B11: =Raw_Data!C29 -> 0.68045792
A12: Fixed NGL Revenue ($M) | B12: =Raw_Data!F6 -> 79.346
A14: Item | B14: 45 | C14: 55 | D14: 65 | E14: 70.29 | F14: 80 | G14: 90 | H14: The Break even point | I14: 49.8
A15: Oil Price Scenario | B15: 45 | C15: 55 | D15: 65 | E15: 70.29 | F15: 80 | G15: 90 | H15: 49.8
A16: Oil Revenue ($M) | B16: =B15*$B$2 -> 1422 | C16: =C15*$B$2 -> 1738 | D16: =D15*$B$2 -> 2054 | E16: =E15*$B$2 -> 2221.164 | F16: =F15*$B$2 -> 2528 | G16: =G15*$B$2 -> 2844 | H16: =H15*$B$2 -> 1573.68
A17: Gas Revenue ($M) | B17: =$B$3 -> 425.39 | C17: =$B$3 -> 425.39 | D17: =$B$3 -> 425.39 | E17: =$B$3 -> 425.39 | F17: =$B$3 -> 425.39 | G17: =$B$3 -> 425.39 | H17: =$B$3 -> 425.39
A18: Total Revenue ($M) | B18: =B16+B17+$B$12 -> 1926.736 | C18: =C16+C17+$B$12 -> 2242.736 | D18: =D16+D17+$B$12 -> 2558.736 | E18: =E16+E17+$B$12 -> 2725.9 | F18: =F16+F17+$B$12 -> 3032.736 | G18: =G16+G17+$B$12 -> 3348.736 | H18: =H16+H17+$B$12 -> 2078.416
A19: Royalties ($M) | B19: =B18*$B$4 -> 335.95422 | C19: =C18*$B$4 -> 391.05338 | D19: =D18*$B$4 -> 446.15254 | E19: =E18*$B$4 -> 475.3 | F19: =F18*$B$4 -> 528.80128 | G19: =G18*$B$4 -> 583.90044 | H19: =H18*$B$4 -> 362.40182
A20: Production Costs ($M) | B20: =$B$5 -> 752.6 | C20: =$B$5 -> 752.6 | D20: =$B$5 -> 752.6 | E20: =$B$5 -> 752.6 | F20: =$B$5 -> 752.6 | G20: =$B$5 -> 752.6 | H20: =$B$5 -> 752.6
A21: DD& A ($M) | B21: =$B$6 -> 549.2 | C21: =$B$6 -> 549.2 | D21: =$B$6 -> 549.2 | E21: =$B$6 -> 549.2 | F21: =$B$6 -> 549.2 | G21: =$B$6 -> 549.2 | H21: =$B$6 -> 549.2
A22: Regulatory Fees ($M) | B22: =$B$7 -> 44.2 | C22: =$B$7 -> 44.2 | D22: =$B$7 -> 44.2 | E22: =$B$7 -> 44.2 | F22: =$B$7 -> 44.2 | G22: =$B$7 -> 44.2 | H22: =$B$7 -> 44.2
A23: G&A ($M) | B23: =$B$8 -> 249.5 | C23: =$B$8 -> 249.5 | D23: =$B$8 -> 249.5 | E23: =$B$8 -> 249.5 | F23: =$B$8 -> 249.5 | G23: =$B$8 -> 249.5 | H23: =$B$8 -> 249.5
A24: Other Income ($M) | B24: =$B$9 -> 57.5 | C24: =$B$9 -> 57.5 | D24: =$B$9 -> 57.5 | E24: =$B$9 -> 57.5 | F24: =$B$9 -> 57.5 | G24: =$B$9 -> 57.5 | H24: =$B$9 -> 57.5
A25: Net Finance Costs ($M) | B25: =$B$10 -> 177.4 | C25: =$B$10 -> 177.4 | D25: =$B$10 -> 177.4 | E25: =$B$10 -> 177.4 | F25: =$B$10 -> 177.4 | G25: =$B$10 -> 177.4 | H25: =$B$10 -> 177.4
A26: Profit Before Tax ($M) | B26: =B18-B19-B20-B21-B22-B23+B24-$B$25 -> -124.61822 | C26: =C18-C19-C20-C21-C22-C23+C24-$B$25 -> 136.28262 | D26: =D18-D19-D20-D21-D22-D23+D24-$B$25 -> 397.18346 | E26: =E18-E19-E20-E21-E22-E23+E24-$B$25 -> 535.2 | F26: =F18-F19-F20-F21-F22-F23+F24-$B$25 -> 788.53472 | G26: =G18-G19-G20-G21-G22-G23+G24-$B$25 -> 1049.4356 | H26: =H18-H19-H20-H21-H22-H23+H24-$B$25 -> 0.61417866
A27: Tax ($M) | B27: =B26*$B$11 -> -84.797458 | C27: =C26*$B$11 -> 92.734586 | D27: =D26*$B$11 -> 270.26663 | E27: =E26*$B$11 -> 364.18108 | F27: =F26*$B$11 -> 536.5647 | G27: =G26*$B$11 -> 714.09674 | H27: =H26*$B$11 -> 0.41792273
A28: Net Income ($M) | B28: =B26-B$27 -> -39.820766 | C28: =C26-C$27 -> 43.54803 | D28: =D26-D$27 -> 126.91683 | E28: =E26-E$27 -> 171.01892 | F28: =F26-F$27 -> 251.97002 | G28: =G26-G$27 -> 335.33882 | H28: =H26-H$27 -> 0.19625592
K32: Model's calculated Profit Before Tax at actual FY2025 oil price ($70.29) is $535.2M vs. actual reported $497.8M (variance: $37.4M / 7.5%). Variance attributable to additional non-operating/financing items in Seplat's accounts not separately captured in this model. Model methodology and directional sensitivity (i.e., how Net Income responds to oil price changes) remain valid; absolute dollar values carry an approximate 7% uncertainty band.Sensitivity outputs below should be read as directional indicators of profit exposure to oil price movements, not as precise point forecasts. | N32: The approx. Break even point is $49.80M
K34: T
